ErrorFile/__init__.py
ErrorFile/Detection/ArchiveInspector.py
ErrorFile/Detection/ExcelInspector.py
ErrorFile/Detection/FileInspector.py
ErrorFile/Detection/ImageInspector_precise.py
ErrorFile/Detection/MediaInspector.py
ErrorFile/Detection/PDFInspector.py
ErrorFile/Detection/PowerPointInspector.py
ErrorFile/Detection/WordInspector.py
ErrorFile/Detection/__init__.py
ErrorFile/Repair/__init__.py
errorfile-0.1.8.dist-info/licenses/LICENSE
tests/__init__.py
tests/good_xls_bytes.py
tests/sample_binary_assets.py
tests/test_inspector.py
errorfile-0.1.8.dist-info/METADATA
errorfile-0.1.8.dist-info/WHEEL
errorfile-0.1.8.dist-info/top_level.txt
errorfile-0.1.8.dist-info/RECORD
