Metadata-Version: 2.4
Name: ErrorFile
Version: 0.1.8
Summary: 一个用于检测图片、文档、压缩包与媒体文件是否损坏的Python包
Home-page: https://github.com/Hellohistory/Errorfile
Author: Hellohistory
Author-email: etojsyc521@gmail.com
Project-URL: Bug Reports, https://github.com/Hellohistory/Errorfile/issues
Project-URL: Source, https://github.com/Hellohistory/Errorfile
Keywords: error file check corrupt damage inspector
Classifier: Development Status :: 3 - Alpha
Classifier: Intended Audience :: Developers
Classifier: Topic :: Software Development :: Libraries
Classifier: License :: OSI Approved :: Apache Software License
Classifier: Programming Language :: Python :: 3
Classifier: Programming Language :: Python :: 3.7
Classifier: Programming Language :: Python :: 3.8
Classifier: Programming Language :: Python :: 3.9
Classifier: Programming Language :: Python :: 3.10
Classifier: Programming Language :: Python :: 3.11
Classifier: Programming Language :: Python :: 3.12
Classifier: Programming Language :: Python :: 3.13
Requires-Python: >=3.7
License-File: LICENSE
Requires-Dist: pypdf2
Requires-Dist: Pillow<10.5.0,>=10.4.0
Requires-Dist: openpyxl
Requires-Dist: xlrd
Requires-Dist: python-docx
Requires-Dist: python-pptx
Requires-Dist: rarfile
Requires-Dist: mutagen
Dynamic: author
Dynamic: author-email
Dynamic: classifier
Dynamic: description
Dynamic: description-content-type
Dynamic: home-page
Dynamic: keywords
Dynamic: license-file
Dynamic: project-url
Dynamic: requires-dist
Dynamic: requires-python
Dynamic: summary
